{
 "@confidence": "0.5",
 "@text": "RT @DeanWye: The force is strong with our film and TV trail https://t.co/seUMWVgVMi #deanwyefilm #starwars https://t.co/5S0sUQaKVe",
 "@support": "20",
 "@types": "",
 "Resources": [
  {
   "@percentageOfSecondRank": "0.0019498818743195502",
   "@URI": "http://dbpedia.org/resource/RT_(TV_network)",
   "@support": "408",
   "@surfaceForm": "RT",
   "@offset": "0",
   "@similarityScore": "0.9963160834553428",
   "@types": "DBpedia:Agent,Schema:Organization,DBpedia:Organisation,DBpedia:Broadcaster,Schema:TelevisionStation,DBpedia:TelevisionStation"
  },
  {
   "@percentageOfSecondRank": "0.005259138526821592",
   "@URI": "http://dbpedia.org/resource/Force",
   "@support": "4917",
   "@surfaceForm": "force",
   "@offset": "17",
   "@similarityScore": "0.9890342810280922",
   "@types": ""
  }
 ],
 "tweet": "677036829623918592",
 "@sparql": "",
 "@policy": "whitelist"
}