{"@confidence":"0.5","@text":"RT @StarWarsJunk: Fan art #StarWars #TheForceAwakens #rey @dailyridley https://t.co/n3KRh5wF3F","@support":"20","@types":"","Resources":[{"@percentageOfSecondRank":"0.0334531827645843","@URI":"http://dbpedia.org/resource/RT_(TV_network)","@support":"408","@surfaceForm":"RT","@offset":"0","@similarityScore":"0.9419574474865323","@types":"DBpedia:Agent,Schema:Organization,DBpedia:Organisation,DBpedia:Broadcaster,Schema:TelevisionStation,DBpedia:TelevisionStation"}],"tweet":"675222404961050628","@sparql":"","@policy":"whitelist"}