{"@confidence":"0.5","@text":"Yeah, #Trump's a clown, but I'm enjoying the fact that he's the fruition of the #GOP's racist mid-20th century \"southern strategy.\" #Bernie","@support":"20","@types":"","Resources":[{"@percentageOfSecondRank":"1.3367873003171515E-4","@URI":"http://dbpedia.org/resource/Clown","@support":"1058","@surfaceForm":"clown","@offset":"17","@similarityScore":"0.9996269493247609","@types":""},{"@percentageOfSecondRank":"1.2793305478057797E-4","@URI":"http://dbpedia.org/resource/Republican_Party_(United_States)","@support":"60935","@surfaceForm":"GOP","@offset":"81","@similarityScore":"0.9998429084502655","@types":"DBpedia:Agent,Schema:Organization,DBpedia:Organisation,DBpedia:PoliticalParty"},{"@percentageOfSecondRank":"6.44696451658788E-7","@URI":"http://dbpedia.org/resource/Southern_strategy","@support":"71","@surfaceForm":"southern strategy","@offset":"112","@similarityScore":"0.9999993553039221","@types":""}],"tweet":"675575915808731136","@sparql":"","@policy":"whitelist"}