{
 "@confidence": "0.5",
 "@text": "RT @RosannaPansino: Big thank you to @Disney for inviting me to the World Premiere of #StarWars #TheForceAwakens! Loved every minute ðŸ\u2019\u2022 httpâ\u20ac¦",
 "@support": "20",
 "@types": "",
 "Resources": [
  {
   "@percentageOfSecondRank": "0.0015336359663794656",
   "@URI": "http://dbpedia.org/resource/RT_(TV_network)",
   "@support": "408",
   "@surfaceForm": "RT",
   "@offset": "0",
   "@similarityScore": "0.9968755751309587",
   "@types": "DBpedia:Agent,Schema:Organization,DBpedia:Organisation,DBpedia:Broadcaster,Schema:TelevisionStation,DBpedia:TelevisionStation"
  },
  {
   "@percentageOfSecondRank": "0.0030440235856410607",
   "@URI": "http://dbpedia.org/resource/The_Walt_Disney_Company",
   "@support": "12715",
   "@surfaceForm": "Disney",
   "@offset": "38",
   "@similarityScore": "0.9944078696051378",
   "@types": "DBpedia:Agent,Schema:Organization,DBpedia:Organisation,DBpedia:Company"
  }
 ],
 "tweet": "676782680852135937",
 "@sparql": "",
 "@policy": "whitelist"
}